adr_builder/__init__.py
adr_builder/cli.py
adr_builder/config.py
adr_builder/fs.py
adr_builder/generator.py
adr_builder/models.py
adr_builder/py.typed
adr_builder/validator.py
adr_builder/templates/hld.md.j2
adr_builder/templates/lld.md.j2
adr_builder/templates/madr.md.j2
adr_builder-0.1.9.dist-info/METADATA
adr_builder-0.1.9.dist-info/WHEEL
adr_builder-0.1.9.dist-info/entry_points.txt
adr_builder-0.1.9.dist-info/top_level.txt
adr_builder-0.1.9.dist-info/RECORD
