Metadata-Version: 2.4
Name: adr-builder
Version: 0.1.9
Summary: Generate Architectural Decision Records from simple criteria data.
Author: ADR Builder Contributors
License-Expression: MIT
Requires-Python: >=3.9
Requires-Dist: typer[all]>=0.12.0
Requires-Dist: pydantic>=2.6.0
Requires-Dist: PyYAML>=6.0.1
Requires-Dist: Jinja2>=3.1.2
Requires-Dist: rich>=13.7.0
Provides-Extra: docx
Requires-Dist: python-docx>=1.1.0; extra == "docx"
Provides-Extra: dev
Requires-Dist: pytest>=8.0.0; extra == "dev"
Requires-Dist: pytest-cov>=4.1.0; extra == "dev"
Requires-Dist: mypy>=1.8.0; extra == "dev"
Requires-Dist: ruff>=0.2.0; extra == "dev"
Requires-Dist: pre-commit>=3.6.0; extra == "dev"
Requires-Dist: types-PyYAML>=6.0.0; extra == "dev"
